[
{"shop":"XXL STORO", "product":"Overwatch", "price":200.00},
{"shop":"REMA 1000", "product":"Minecraft", "price":125.50},
{"shop":"ICA MAXI", "product":"Fortnite", "price":510.00},
{"shop":"IKEA Furuset", "product":"Stor Seng", "price":5430.50},
{"shop":"JOKA FRYSJA", "product":"KIDNEY BØNNER ELDORADO", "price":7.50},
{"shop":"JOKA KJELSÅS", "product":"KIDNEY BØNNER ELDORADO", "price":7.50},
{"shop":"REMA 1000", "product":"TOMAT HEL 1/2BX ELDORADO", "price":8.90},
{"shop":"JOKA FRYSJA", "product":"KNEKKEBRØD RUNDA KANEL", "price":48.90},
{"shop":"JOKA KJELSÅS", "product":"ALUMINIUMFOLIE TYKK 45", "price":22.90},
{"shop":"JOKA FRYSJA", "product":"KYLLING OVERLØR 600G", "price":59.90},
{"shop":"REMA 1000", "product":"KYLLING OVERLØR 600G", "price":59.90},
{"shop":"REMA 1000", "product":"LØK STRØMPE 25ST 450G", "price":17.90},
{"shop":"REMA 1000", "product":"AASS FATØL 0.5L BX", "price":35.90},
{"shop":"JOKA KJELSÅS", "product":"CHILINØTTER 175G ELDORADO", "price":10.00},
{"shop":"JOKA KJELSÅS", "product":"COLGATE TANNKREM KARIES", "price":18.90},
{"shop":"ICA MAXI", "product":"LANO SØPE 2x125G", "price":23.50},
{"shop":"JOKA FRYSJA", "product":"KNEIP BRØD 750G FIRST", "price":7.90},
{"shop":"JOKA FRYSJA", "product":"BÆREPOSE", "price":2.00}
]
